fivesimbiz/__init__.py
fivesimbiz/main.py
fivesimbiz-1.0.0.dist-info/METADATA
fivesimbiz-1.0.0.dist-info/WHEEL
fivesimbiz-1.0.0.dist-info/top_level.txt
fivesimbiz-1.0.0.dist-info/RECORD
